siembra/__init__.py
siembra/__main__.py
siembra/safepaths.py
siembra/siembra.py
siembra/temp_files.py
siembra/v0_1/__init__.py
siembra/v0_1/installer.py
siembra/v0_1/validator.py
siembra/v0_1/executors/__init__.py
siembra/v0_1/executors/docker.py
siembra/v0_1/executors/file.py
siembra/v0_1/executors/template.py
siembra-0.1.12.dist-info/METADATA
siembra-0.1.12.dist-info/WHEEL
siembra-0.1.12.dist-info/entry_points.txt
siembra-0.1.12.dist-info/top_level.txt
siembra-0.1.12.dist-info/RECORD
