Metadata-Version: 2.1
Name: siembra
Version: 0.1.12
Summary: Description
Home-page: https://github.com/mulitadev/siembra
Author: Juan Cabrera
Author-email: juan@jjcp.dev
License: UNKNOWN
Platform: UNKNOWN
Classifier: Programming Language :: Python :: 3
Classifier: License :: OSI Approved :: MIT License
Classifier: Operating System :: OS Independent
Requires-Python: >= 3.8
Requires-Dist: docopt (==0.6.2)
Requires-Dist: PyYAML (==5.3.1)
Requires-Dist: schema (==0.7.2)
